flask_dynamo/__init__.py
flask_dynamo/errors.py
flask_dynamo/manager.py
flask_dynamo-0.1.2.dist-info/DESCRIPTION.rst
flask_dynamo-0.1.2.dist-info/METADATA
flask_dynamo-0.1.2.dist-info/RECORD
flask_dynamo-0.1.2.dist-info/WHEEL
flask_dynamo-0.1.2.dist-info/metadata.json
flask_dynamo-0.1.2.dist-info/top_level.txt
